zscams/__init__.py
zscams/__main__.py
zscams/agent/__init__.py
zscams/agent/certificates/.gitkeep
zscams/agent/config.yaml
zscams/agent/configuration/config.j2
zscams/agent/configuration/freebsd_service.j2
zscams/agent/configuration/linux_service.j2
zscams/agent/keys/autoport.key
zscams/agent/src/__init__.py
zscams/agent/src/core/__init__.py
zscams/agent/src/core/backend/bootstrap.py
zscams/agent/src/core/backend/client.py
zscams/agent/src/core/backend/exceptions.py
zscams/agent/src/core/backend/unbootstrap.py
zscams/agent/src/core/backend/update_machine_info.py
zscams/agent/src/core/prerequisites.py
zscams/agent/src/core/service_health_check.py
zscams/agent/src/core/services.py
zscams/agent/src/core/tunnel/__init__.py
zscams/agent/src/core/tunnel/tls.py
zscams/agent/src/core/tunnels.py
zscams/agent/src/services/__init__.py
zscams/agent/src/services/reverse_ssh.py
zscams/agent/src/services/ssh_forwarder.py
zscams/agent/src/services/system_monitor.py
zscams/agent/src/support/__init__.py
zscams/agent/src/support/cli.py
zscams/agent/src/support/configuration.py
zscams/agent/src/support/filesystem.py
zscams/agent/src/support/logger.py
zscams/agent/src/support/mac.py
zscams/agent/src/support/network.py
zscams/agent/src/support/openssl.py
zscams/agent/src/support/os.py
zscams/agent/src/support/ssh.py
zscams/agent/src/support/yaml.py
zscams/deps.py
zscams/lib/.gitkeep
zscams-2.0.9.dist-info/METADATA
zscams-2.0.9.dist-info/WHEEL
zscams-2.0.9.dist-info/entry_points.txt
zscams-2.0.9.dist-info/RECORD
