Metadata-Version: 2.1
Name: zscams
Version: 2.0.9
Summary: Async TLS tunnel client with SNI routing, auto-reconnect, and health checks
Author: OCD - Cairo Software Team
Maintainer: OCD - Cairo Software Team
Requires-Python: >=3.9
Classifier: Programming Language :: Python :: 3
Classifier: Programming Language :: Python :: 3.9
Classifier: Programming Language :: Python :: 3.10
Classifier: Programming Language :: Python :: 3.11
Classifier: Programming Language :: Python :: 3.12
Classifier: Programming Language :: Python :: 3.13
Requires-Dist: getmac
Requires-Dist: requests
